[
    {
        "page_number": 6,
        "link": "https://github.com/MooreThreads/TurboRAG"
    },
    {
        "page_number": 10,
        "link": "https://arxiv.org/abs/1810.04805"
    },
    {
        "page_number": 10,
        "link": "https://arxiv.org/abs/1810.04805"
    },
    {
        "page_number": 10,
        "link": "https://arxiv.org/abs/2208.03299"
    },
    {
        "page_number": 10,
        "link": "https://arxiv.org/abs/2208.03299"
    },
    {
        "page_number": 11,
        "link": "https://arxiv.org/abs/1911.00172"
    },
    {
        "page_number": 11,
        "link": "https://arxiv.org/abs/1911.00172"
    },
    {
        "page_number": 11,
        "link": "https://arxiv.org/abs/2212.10511"
    }
]